Metadata-Version: 2.1
Name: cython-compiler
Version: 1.0.2
Summary: Cythonize your project, securing it's source, while still be able to test with python and bundle with PyInstaller
Home-page: https://github.com/JessicaTegner/cython-compiler
Author: JessicaTegner
License: GNU LGPLv3
Keywords: cython cythonize pyinstaller
Classifier: Development Status :: 4 - Beta
Classifier: Environment :: Console
Classifier: Intended Audience :: Developers
Classifier: License :: OSI Approved :: GNU Lesser General Public License v3 (LGPLv3)
Classifier: Topic :: Software Development :: Build Tools
Classifier: Operating System :: OS Independent
Classifier: Programming Language :: Python :: 3.4
Classifier: Programming Language :: Python :: 3.5
Classifier: Programming Language :: Python :: 3.6
Classifier: Programming Language :: Python :: 3.7
License-File: LICENSE
